README.md
setup.cfg
setup.py
openapi_client/__init__.py
openapi_client/api_client.py
openapi_client/configuration.py
openapi_client/exceptions.py
openapi_client/rest.py
openapi_client/api/__init__.py
openapi_client/api/default_api.py
openapi_client/models/__init__.py
openapi_client/models/assessment_type.py
openapi_client/models/ats_type.py
openapi_client/models/configuration.py
openapi_client/models/error_response.py
openapi_client/models/list_orders_request.py
openapi_client/models/list_orders_response.py
openapi_client/models/mercury_assessment.py
openapi_client/models/mercury_assessment_order.py
openapi_client/models/mercury_candidate.py
openapi_client/models/mercury_development_report_content.py
openapi_client/models/mercury_factor_content.py
openapi_client/models/mercury_model_direction.py
openapi_client/models/mercury_order_factor_content.py
openapi_client/models/mercury_order_metadata.py
openapi_client/models/mercury_report.py
openapi_client/models/mercury_result.py
openapi_client/models/mercury_retrieve_factor_content_request.py
openapi_client/models/o_auth_request.py
openapi_client/models/o_auth_response.py
openapi_client/models/order_create_response.py
openapi_client/models/order_request.py
openapi_client/models/pontem_order_statuses.py
openapi_client/models/pontem_report_types.py
pymetrics_soft_skills_sdk/__init__.py
pymetrics_soft_skills_sdk/api_client.py
pymetrics_soft_skills_sdk/configuration.py
pymetrics_soft_skills_sdk/exceptions.py
pymetrics_soft_skills_sdk/rest.py
pymetrics_soft_skills_sdk.egg-info/PKG-INFO
pymetrics_soft_skills_sdk.egg-info/SOURCES.txt
pymetrics_soft_skills_sdk.egg-info/dependency_links.txt
pymetrics_soft_skills_sdk.egg-info/requires.txt
pymetrics_soft_skills_sdk.egg-info/top_level.txt
pymetrics_soft_skills_sdk/api/__init__.py
pymetrics_soft_skills_sdk/api/default_api.py
pymetrics_soft_skills_sdk/models/__init__.py
pymetrics_soft_skills_sdk/models/assessment_type.py
pymetrics_soft_skills_sdk/models/ats_type.py
pymetrics_soft_skills_sdk/models/configuration.py
pymetrics_soft_skills_sdk/models/error_response.py
pymetrics_soft_skills_sdk/models/list_orders_request.py
pymetrics_soft_skills_sdk/models/list_orders_response.py
