Metadata-Version: 2.1
Name: pymetrics-soft-skills-sdk
Version: 1.0.2
Summary: pymetrics API
Home-page: UNKNOWN
Author: OpenAPI Generator community
Author-email: team@openapitools.org
License: UNKNOWN
Keywords: OpenAPI,OpenAPI-Generator,pymetrics API
Platform: UNKNOWN
